DataPilot/AI_API.py
DataPilot/DataAnalysis.py
DataPilot/DataPreprocessing.py
DataPilot/DataSource.py
DataPilot/NN.py
DataPilot/__init__.py
data_pilot-0.0.2.dist-info/METADATA
data_pilot-0.0.2.dist-info/WHEEL
data_pilot-0.0.2.dist-info/RECORD
